PISO.v


module piso_shift_register (input clk,rst,load,input wire [3:0] in,output wire out);

reg [3:0] q;

  always @(posedge clk or negedge rst) begin
    if (!rst) begin
        q <= 4'b0000;
      
    end else begin 
        if (!load) begin
           q <= in;
          
        end else begin
            q <= {1'b0, q[3:1]};
        end
    end
end


assign out = q[0];

endmodule


module piso_shift_register_tb;
    reg clk;
    reg rst;
    reg load;
  reg [3:0] in;
    wire out;

    piso_shift_register uut (.clk(clk),.rst(rst),.load(load),.in(in),.out(out));

    initial begin
        clk = 0;
        forever #5 clk = ~clk;
    end

    initial begin
      
       $dumpfile("piso_shift_register_tb.vcd");
        $dumpvars(0, piso_shift_register_tb);

        rst = 0; load = 1;
        #12 rst = 1; 

        #10 load = 0; in = 4'b1011;
        @(posedge clk);
        #1;
        load = 1;

        repeat(4) begin
            @(posedge clk);
          $display("Time=%0t | S_Out=%b | P_input =%b", $time, out,in);
        end

        #10 load = 0; in = 4'b0110;
      @(posedge clk);#1;
        load = 1;

        repeat(4) begin
         @(posedge clk);
          $display("Time=%0t | S_Out=%b| P_input =%b", $time,out,in);
        end
        #20;
        $display("Simulation completed.");
        $finish;
    end

endmodule

piso_shift_register_tb.vcd
$date
	Sat Sep 27 12:21:26 2025
$end
$version
	ModelSim Version 10.5b
$end
$timescale
	1ps
$end

$scope module piso_shift_register_tb $end
$var reg 1 ! clk $end
$var reg 1 " rst $end
$var reg 1 # load $end
$var reg 4 $ in [3:0] $end
$var wire 1 % out $end

$scope module uut $end
$var wire 1 & clk $end
$var wire 1 ' rst $end
$var wire 1 ( load $end
$var wire 1 ) in [3] $end
$var wire 1 * in [2] $end
$var wire 1 + in [1] $end
$var wire 1 , in [0] $end
$var wire 1 % out $end
$var reg 4 - q [3:0] $end
$upscope $end
$upscope $end
$enddefinitions $end
#0
$dumpvars
0!
0"
1#
bx $
b0 -
0%
x,
x+
x*
x)
1(
0'
0&
$end
#5
1!
1&
#10
0!
0&
#12
1"
1'
#15
1!
1&
#20
0!
0&
#22
0#
b1011 $
0(
1,
1+
0*
1)
#25
1!
1&
b1011 -
1%
#26
1#
1(
#30
0!
0&
#35
1!
1&
b101 -
#40
0!
0&
#45
1!
1&
b10 -
0%
#50
0!
0&
#55
1!
1&
b1 -
1%
#60
0!
0&
#65
1!
1&
b0 -
0%
#70
0!
0&
#75
0#
b110 $
1!
0(
0,
1*
0)
1&
b110 -
#76
1#
1(
#80
0!
0&
#85
1!
1&
b11 -
1%
#90
0!
0&
#95
1!
1&
b1 -
#100
0!
0&
#105
1!
1&
b0 -
0%
